{
  "page_id": "3011088481",
  "title": "2. Autosar OS Task - Types, Priority",
  "version": 5,
  "url": "/spaces/CARSFW/pages/3011088481/2.+Autosar+OS+Task+-+Types+Priority",
  "last_modified": "2023-05-06T08:22:14.000+02:00",
  "last_modified_by": "Jayaraj Praveen (BCSC/ENG1)",
  "parent_id": "3011088327",
  "children": [],
  "content": [
    {
      "type": "heading",
      "level": 1,
      "text": "Tasks"
    },
    {
      "type": "paragraph",
      "text": "Two different task concepts are provided by the OSEK operating system"
    },
    {
      "type": "list",
      "ordered": false,
      "items": [
        "basic tasks",
        "extended tasks"
      ]
    },
    {
      "type": "heading",
      "level": 2,
      "text": "Basic Tasks"
    },
    {
      "type": "paragraph",
      "text": "Basic Tasks have only three states as shown below"
    },
    {
      "type": "image",
      "src": "https://inside-docupedia.bosch.com/confluence/download/attachments/embedded-page/CARSFW/2.%20Autosar%20OS%20Task%20-%20Types,%20Priority/image-2023-5-6_13-50-0.png?api=v2",
      "alt": "",
      "local_path": "_images/2. Autosar OS Task - Types, Priority/image-2023-5-6_13-50-0.png"
    },
    {
      "type": "paragraph",
      "text": "Basic tasks only release the processor if"
    },
    {
      "type": "list",
      "ordered": false,
      "items": [
        "they terminate",
        "operating system switches to a higher-priority task (If the task is configured as Preemptable)",
        "an interrupt occurs which causes the processor to switch to an interrupt service routine (ISR)"
      ]
    },
    {
      "type": "heading",
      "level": 2,
      "text": "Extended Tasks"
    },
    {
      "type": "paragraph",
      "text": "Extended tasks are distinguished from basic tasks by being allowed to use the operating system call WaitEvent, which may result in a waiting state"
    },
    {
      "type": "image",
      "src": "https://inside-docupedia.bosch.com/confluence/download/attachments/embedded-page/CARSFW/2.%20Autosar%20OS%20Task%20-%20Types,%20Priority/image-2023-5-6_13-58-9.png?api=v2",
      "alt": "",
      "local_path": "_images/2. Autosar OS Task - Types, Priority/image-2023-5-6_13-58-9.png"
    },
    {
      "type": "heading",
      "level": 2,
      "text": "Task priority"
    },
    {
      "type": "paragraph",
      "text": "The scheduler decides on the basis of the task priority which is the next of the ready tasks to be transferred into the running state"
    },
    {
      "type": "panel",
      "panel_type": "info",
      "title": "Dynamic Priority",
      "content": "To enhance efficiency, a dynamic priority management is not supported. Accordingly the priority of a task is defined statically, i.e. the user cannot change it at the time of execution. However, in particular cases the operating system can treat a task with a defined higher priority (Priority Ceiling Protocol)"
    },
    {
      "type": "paragraph",
      "text": "Tasks on the same priority level are started depending on their order of activation,"
    },
    {
      "type": "paragraph",
      "text": "A preempted task is considered to be the first (oldest) task in the ready list of its current priority"
    },
    {
      "type": "image",
      "src": "https://inside-docupedia.bosch.com/confluence/download/attachments/embedded-page/CARSFW/2.%20Autosar%20OS%20Task%20-%20Types,%20Priority/image-2023-5-6_14-20-38.png?api=v2",
      "alt": "",
      "local_path": "_images/2. Autosar OS Task - Types, Priority/image-2023-5-6_14-20-38.png"
    },
    {
      "type": "paragraph",
      "text": "The following fundamental steps are necessary to determine the next task to be processed:"
    },
    {
      "type": "list",
      "ordered": false,
      "items": [
        "Step 1: The scheduler searches for all tasks in the ready/running state.",
        "Step 2: From the set of tasks in the ready/running state, the scheduler determines the set of tasks with the highest priority.",
        "Step 3: Within the set of tasks in the ready/running state and of highest priority, the scheduler finds the oldest task."
      ]
    }
  ],
  "attachments": [
    {
      "title": "image-2023-5-6_14-20-38.png",
      "download_link": "/download/attachments/3011088481/image-2023-5-6_14-20-38.png?version=1&modificationDate=1683354038000&api=v2",
      "local_path": ""
    },
    {
      "title": "image-2023-5-6_13-50-0.png",
      "download_link": "/download/attachments/3011088481/image-2023-5-6_13-50-0.png?version=1&modificationDate=1683353151000&api=v2",
      "local_path": ""
    },
    {
      "title": "image-2023-5-6_13-58-9.png",
      "download_link": "/download/attachments/3011088481/image-2023-5-6_13-58-9.png?version=1&modificationDate=1683353151000&api=v2",
      "local_path": ""
    }
  ]
}