{
  "page_id": "4642135043",
  "title": "SWC_OCD_Warnings_Telltales_SRC",
  "version": 15,
  "url": "/spaces/CARSFW/pages/4642135043/SWC_OCD_Warnings_Telltales_SRC",
  "last_modified": "2026-04-14T08:35:01.000+02:00",
  "last_modified_by": "LI Minsheng (XC-CP/ESW2-CN)",
  "parent_id": "4565826990",
  "children": [],
  "content": [
    {
      "type": "heading",
      "level": 1,
      "text": "1. 概要：座舱系统的仪表侧支持一些提示类或报警类的信息展示，简称Warning，这些信息给与驾驶员指导性操作或提示故障及风险；"
    },
    {
      "type": "heading",
      "level": 1,
      "text": "2. 需求文档："
    },
    {
      "type": "code_block",
      "language": "",
      "content": "PIS-2062 Cluster Telltale Requirement.docx"
    },
    {
      "type": "code_block",
      "language": "",
      "content": "PIS-2047_EngineeringMode.docx"
    },
    {
      "type": "code_block",
      "language": "",
      "content": "PIS-2076 Cluster General Requirement.docx"
    },
    {
      "type": "code_block",
      "language": "",
      "content": "PIS-2085 IPC SW Specification V3.1.docx"
    },
    {
      "type": "code_block",
      "language": "",
      "content": "……"
    },
    {
      "type": "code_block",
      "language": "",
      "content": "Warning列表：PIS-2069 Cluster Warning Requirement(effect ICS&HUD).xlsx"
    },
    {
      "type": "paragraph",
      "text": "（以客户最新为准）"
    },
    {
      "type": "heading",
      "level": 1,
      "text": "3. 模块分析："
    },
    {
      "type": "heading",
      "level": 2,
      "text": "3.1. Warning集合介绍："
    },
    {
      "type": "paragraph",
      "text": "目前分析是两大类（有变更后续在补充）"
    },
    {
      "type": "paragraph",
      "text": "第一类：根据电源状态控制，PM RUN Property = \"Yes\"，电源切换由RUN切换到ACC、OFF时，不再提示；"
    },
    {
      "type": "paragraph",
      "text": "第二类：不受电源状态影响，PM RUN Property = \"No\"，电源切换到非RUN，也会判定提示；"
    },
    {
      "type": "paragraph",
      "text": "还有个特殊的子集，某些Warning有延时处理的逻辑需求，有个单独的Mapping表，在周期性任务中会判定超时，再进一步处理；"
    },
    {
      "type": "paragraph",
      "text": "代码中：用Warning ID的区间，进行了种类的区分；"
    },
    {
      "type": "image",
      "src": "https://inside-docupedia.bosch.com/confluence/download/attachments/embedded-page/CARSFW/SWC_OCD_Warnings_Telltales_SRC/image-2024-8-27_13-52-52.png?api=v2",
      "alt": "",
      "local_path": "_images/SWC_OCD_Warnings_Telltales_SRC/image-2024-8-27_13-52-52.png"
    },
    {
      "type": "paragraph",
      "text": "非can总线信号触发的Warning："
    },
    {
      "type": "paragraph",
      "text": "CLEA部分：Warning #9601-9604"
    },
    {
      "type": "paragraph",
      "text": "GB部分：Warning #8001 -8002 / Warning #8100+(GB L2++项目Only)"
    },
    {
      "type": "heading",
      "level": 2,
      "text": "3.2. Warning提示种类："
    },
    {
      "type": "table",
      "headers": [
        "",
        ""
      ],
      "rows": [
        [
          "Chime音效",
          "Chime ID - 0 不需要触发Chime Chime ID - 具体数值标明Warning触发的Chime的ID"
        ],
        [
          "显示在HUD",
          "抬头显示，此项紧CLEA适用？？"
        ],
        [
          "显示在IPC上",
          "仪表"
        ],
        [
          "显示在ICS上",
          "中控"
        ],
        [
          "",
          ""
        ]
      ]
    },
    {
      "type": "image",
      "src": "https://inside-docupedia.bosch.com/confluence/download/attachments/embedded-page/CARSFW/SWC_OCD_Warnings_Telltales_SRC/image-2024-9-2_10-0-35.png?api=v2",
      "alt": "",
      "local_path": "_images/SWC_OCD_Warnings_Telltales_SRC/image-2024-9-2_10-0-35.png"
    },
    {
      "type": "heading",
      "level": 2,
      "text": "3.3. Warning确认方式："
    },
    {
      "type": "table",
      "headers": [
        "",
        ""
      ],
      "rows": [
        [
          "Manual",
          "可以通过按键，手动确认消失"
        ],
        [
          "ManualAuto",
          "可以通过按键确认消失，也可以超时确认消失"
        ],
        [
          "Auto",
          "可以超时消失，但是不能手动确认消失"
        ],
        [
          "NotAck",
          "既不能手动确认，也不能超时消失"
        ]
      ]
    },
    {
      "type": "heading",
      "level": 2,
      "text": "3.4. 代码分析："
    },
    {
      "type": "table",
      "headers": [
        "",
        ""
      ],
      "rows": [
        [
          "HMI_Warnings.c HMI_Warnings.h",
          "周期执行WarningsTelltales_Run 1、处理Event输入 2、处理Warning的判定和结果执行 3、处理Timer"
        ],
        [
          "maintmdewrningdrvrcnfrmtn_m.c maintmdewrningdrvrcnfrmtn.h",
          "FU218的一个功能实现"
        ],
        [
          "NoActionChime.c",
          "取消Chime event"
        ],
        [
          "SWC_OCD_Warnings_Telltales_ar.h",
          "接口封装"
        ],
        [
          "SWC_OCD_Warnings_telltales_Constants.h",
          "各种宏定义"
        ],
        [
          "SWC_OCD_Warnings_telltales_Variables.c SWC_OCD_Warnings_telltales_Variables.h",
          "全局变量（此函数里多是Chime和功能的定时Timer）"
        ],
        [
          "Warning.c Warning.h",
          "主要Wrn_Run接口，实现对Warning的检测"
        ],
        [
          "WarningAction.h WarningAction.c",
          "表stODI ---- 每个Warning对应的ODI配置 Warining对应的执行，发送HMI通知消息"
        ],
        [
          "WarningCallback.c WarningCallback.h",
          "![](_images/SWC_OCD_Warnings_Telltales_SRC/image-2024-9-2_10-30-36.png)"
        ],
        [
          "WarningData.c WarningData.h",
          "表 WarningT ---- Warning Identifiers 表 trigger ---- Trigger functions for check messages"
        ],
        [
          "WarningTrigger.c WarningTrigger.h",
          "Trigger functions的具体实现"
        ],
        [
          "",
          ""
        ]
      ]
    },
    {
      "type": "paragraph",
      "text": "SWC_OCD_Warnings_Telltal…"
    },
    {
      "type": "paragraph",
      "text": "Warning触发输入分析："
    },
    {
      "type": "image",
      "src": "https://inside-docupedia.bosch.com/confluence/download/attachments/embedded-page/CARSFW/SWC_OCD_Warnings_Telltales_SRC/image-2024-8-28_15-45-38-1.png?api=v2",
      "alt": "",
      "local_path": "_images/SWC_OCD_Warnings_Telltales_SRC/image-2024-8-28_15-45-38-1.png"
    },
    {
      "type": "paragraph",
      "text": "Warning 处理分析："
    },
    {
      "type": "image",
      "src": "https://inside-docupedia.bosch.com/confluence/download/attachments/embedded-page/CARSFW/SWC_OCD_Warnings_Telltales_SRC/image-2024-8-28_15-44-33-1.png?api=v2",
      "alt": "",
      "local_path": "_images/SWC_OCD_Warnings_Telltales_SRC/image-2024-8-28_15-44-33-1.png"
    },
    {
      "type": "paragraph",
      "text": "重要的表："
    },
    {
      "type": "paragraph",
      "text": "表一：Warning ID"
    },
    {
      "type": "paragraph",
      "text": "当收到或触发Warning后，设置Warning event时的Warning ID；"
    },
    {
      "type": "image",
      "src": "https://inside-docupedia.bosch.com/confluence/download/attachments/embedded-page/CARSFW/SWC_OCD_Warnings_Telltales_SRC/image-2024-8-28_15-49-26.png?api=v2",
      "alt": "",
      "local_path": "_images/SWC_OCD_Warnings_Telltales_SRC/image-2024-8-28_15-49-26.png"
    },
    {
      "type": "paragraph",
      "text": "表二：Warning被触发后对应的功能接口函数"
    },
    {
      "type": "image",
      "src": "https://inside-docupedia.bosch.com/confluence/download/attachments/embedded-page/CARSFW/SWC_OCD_Warnings_Telltales_SRC/image-2024-8-28_15-50-45.png?api=v2",
      "alt": "",
      "local_path": "_images/SWC_OCD_Warnings_Telltales_SRC/image-2024-8-28_15-50-45.png"
    },
    {
      "type": "paragraph",
      "text": "表三：Warning对应的ODI配置表；"
    },
    {
      "type": "image",
      "src": "https://inside-docupedia.bosch.com/confluence/download/attachments/embedded-page/CARSFW/SWC_OCD_Warnings_Telltales_SRC/image-2024-8-28_15-52-41.png?api=v2",
      "alt": "",
      "local_path": "_images/SWC_OCD_Warnings_Telltales_SRC/image-2024-8-28_15-52-41.png"
    },
    {
      "type": "paragraph",
      "text": "-------------------------------------------------------------------------------------------------------------------------------------------------------------------------"
    },
    {
      "type": "paragraph",
      "text": "add by mingzong, 对warning的补充"
    },
    {
      "type": "image",
      "src": "https://inside-docupedia.bosch.com/confluence/download/attachments/embedded-page/CARSFW/SWC_OCD_Warnings_Telltales_SRC/image-2026-3-12_14-21-54.png?api=v2",
      "alt": "",
      "local_path": "_images/SWC_OCD_Warnings_Telltales_SRC/image-2026-3-12_14-21-54.png"
    },
    {
      "type": "image",
      "src": "/confluence/download/attachments/4642135043/Untitled%20Diagram-1775185524505.png?version=4&modificationDate=1776148500000&api=v2",
      "alt": "",
      "local_path": "_images/SWC_OCD_Warnings_Telltales_SRC/Untitled Diagram-1775185524505.png"
    }
  ],
  "attachments": [
    {
      "title": "Untitled Diagram-1775185524505",
      "download_link": "/download/attachments/4642135043/Untitled%20Diagram-1775185524505?version=4&modificationDate=1776148500000&api=v2",
      "local_path": ""
    },
    {
      "title": "Untitled Diagram-1775185524505.png",
      "download_link": "/download/attachments/4642135043/Untitled%20Diagram-1775185524505.png?version=4&modificationDate=1776148500000&api=v2",
      "local_path": ""
    },
    {
      "title": "~Untitled Diagram-1775185524505.tmp",
      "download_link": "/download/attachments/4642135043/~Untitled%20Diagram-1775185524505.tmp?version=70&modificationDate=1776067221000&api=v2",
      "local_path": ""
    },
    {
      "title": "image-2026-3-12_14-21-54.png",
      "download_link": "/download/attachments/4642135043/image-2026-3-12_14-21-54.png?version=1&modificationDate=1773296514000&api=v2",
      "local_path": ""
    },
    {
      "title": "image-2024-9-2_10-30-36.png",
      "download_link": "/download/attachments/4642135043/image-2024-9-2_10-30-36.png?version=1&modificationDate=1725244236000&api=v2",
      "local_path": ""
    },
    {
      "title": "image-2024-9-2_10-0-35.png",
      "download_link": "/download/attachments/4642135043/image-2024-9-2_10-0-35.png?version=1&modificationDate=1725242435000&api=v2",
      "local_path": ""
    },
    {
      "title": "image-2024-8-28_15-52-41.png",
      "download_link": "/download/attachments/4642135043/image-2024-8-28_15-52-41.png?version=1&modificationDate=1724831562000&api=v2",
      "local_path": ""
    },
    {
      "title": "image-2024-8-28_15-50-45.png",
      "download_link": "/download/attachments/4642135043/image-2024-8-28_15-50-45.png?version=1&modificationDate=1724831446000&api=v2",
      "local_path": ""
    },
    {
      "title": "image-2024-8-28_15-49-26.png",
      "download_link": "/download/attachments/4642135043/image-2024-8-28_15-49-26.png?version=1&modificationDate=1724831366000&api=v2",
      "local_path": ""
    },
    {
      "title": "image-2024-8-28_15-45-38-1.png",
      "download_link": "/download/attachments/4642135043/image-2024-8-28_15-45-38-1.png?version=1&modificationDate=1724831138000&api=v2",
      "local_path": ""
    },
    {
      "title": "image-2024-8-28_15-44-33-1.png",
      "download_link": "/download/attachments/4642135043/image-2024-8-28_15-44-33-1.png?version=1&modificationDate=1724831074000&api=v2",
      "local_path": ""
    },
    {
      "title": "image-2024-8-28_15-43-43-1.png",
      "download_link": "/download/attachments/4642135043/image-2024-8-28_15-43-43-1.png?version=1&modificationDate=1724831024000&api=v2",
      "local_path": ""
    },
    {
      "title": "SWC_OCD_Warnings_Telltales.drawio",
      "download_link": "/download/attachments/4642135043/SWC_OCD_Warnings_Telltales.drawio?version=1&modificationDate=1724740807000&api=v2",
      "local_path": ""
    },
    {
      "title": "image-2024-8-27_13-52-52.png",
      "download_link": "/download/attachments/4642135043/image-2024-8-27_13-52-52.png?version=1&modificationDate=1724737973000&api=v2",
      "local_path": ""
    },
    {
      "title": "PIS-2062 Cluster Telltale Requirement.docx",
      "download_link": "/download/attachments/4642135043/PIS-2062%20Cluster%20Telltale%20Requirement.docx?version=1&modificationDate=1724736146000&api=v2",
      "local_path": ""
    },
    {
      "title": "PIS-2085 IPC SW Specification V3.1.docx",
      "download_link": "/download/attachments/4642135043/PIS-2085%20IPC%20SW%20Specification%20V3.1.docx?version=1&modificationDate=1724736130000&api=v2",
      "local_path": ""
    },
    {
      "title": "PIS-2076 Cluster General Requirement.docx",
      "download_link": "/download/attachments/4642135043/PIS-2076%20Cluster%20General%20Requirement.docx?version=1&modificationDate=1724736112000&api=v2",
      "local_path": ""
    },
    {
      "title": "PIS-2047_EngineeringMode.docx",
      "download_link": "/download/attachments/4642135043/PIS-2047_EngineeringMode.docx?version=1&modificationDate=1724736106000&api=v2",
      "local_path": ""
    },
    {
      "title": "PIS-2069 Cluster Warning Requirement(effect ICS&HUD).xlsx",
      "download_link": "/download/attachments/4642135043/PIS-2069%20Cluster%20Warning%20Requirement%28effect%20ICS%26HUD%29.xlsx?version=1&modificationDate=1724736072000&api=v2",
      "local_path": ""
    },
    {
      "title": "Worksheet in C  Users wne5sgh Downloads PIS-2069 Cluster Warning Requirement(effect ICS&HUD).xlsx",
      "download_link": "/download/attachments/4642135043/Worksheet%20in%20C%20%20Users%20wne5sgh%20Downloads%20PIS-2069%20Cluster%20Warning%20Requirement%28effect%20ICS%26HUD%29.xlsx?version=1&modificationDate=1724735971000&api=v2",
      "local_path": ""
    }
  ]
}